MANIFEST.in
README.md
setup.py
nc5ng/__init__.py
nc5ng.egg-info/PKG-INFO
nc5ng.egg-info/SOURCES.txt
nc5ng.egg-info/dependency_links.txt
nc5ng.egg-info/top_level.txt
nc5ng/core/__init__.py
nc5ng/core/bicubic.pyf
nc5ng/core/bilin.pyf
nc5ng/core/biquad.pyf
nc5ng/core/bwplotcv.pyf
nc5ng/core/bwplotvc.pyf
nc5ng/core/coplot.pyf
nc5ng/core/coplotwcv.pyf
nc5ng/core/cpt.pyf
nc5ng/core/cpt2.pyf
nc5ng/core/cubterp.pyf
nc5ng/core/getgridbounds.pyf
nc5ng/core/getmag.pyf
nc5ng/core/getmapbounds.pyf
nc5ng/core/gridstats.pyf
nc5ng/core/indexxd.pyf
nc5ng/core/indexxi.pyf
nc5ng/core/iselect2.pyf
nc5ng/core/onzd.pyf
nc5ng/core/onzd2.pyf
nc5ng/core/plotcoast.pyf
nc5ng/core/qterp.pyf
nc5ng/core/select2_dbl.pyf
nc5ng/core/select2_mod.pyf
nc5ng/core/vecstats.pyf
src/Subs/bicubic.f
src/Subs/bilin.f
src/Subs/biquad.f
src/Subs/bwplotcv.f
src/Subs/bwplotvc.f
src/Subs/coplot.f
src/Subs/coplotwcv.f
src/Subs/cpt.f
src/Subs/cpt2.f
src/Subs/cubterp.f
src/Subs/getgridbounds.f
src/Subs/getmag.f
src/Subs/getmapbounds.f
src/Subs/gridstats.f
src/Subs/indexxd.for
src/Subs/indexxi.for
src/Subs/iselect2.for
src/Subs/onzd.f
src/Subs/onzd2.f
src/Subs/plotcoast.f
src/Subs/qterp.f
src/Subs/select2_dbl.for
src/Subs/select2_mod.for
src/Subs/vecstats.f