Metadata-Version: 1.1
Name: nc5ng
Version: 0.0.2
Summary: Python Wrapper for the NADCON5 Datum Transformation Tool
Home-page: https://nc5ng.org
Author: Andrey Shmakov
Author-email: akshmakov@gmail.com
License: UNKNOWN
Download-URL: https://github.com/nc5ng/nadcon5ng
Platform: UNKNOWN
